async_yookassa/__init__.py
async_yookassa/_config.py
async_yookassa/_http.py
async_yookassa/client.py
async_yookassa/enums/__init__.py
async_yookassa/enums/agent_type.py
async_yookassa/enums/deal_enums.py
async_yookassa/enums/delivery_method.py
async_yookassa/enums/fiscalization.py
async_yookassa/enums/invoice_cancellation_details.py
async_yookassa/enums/item_measure.py
async_yookassa/enums/me.py
async_yookassa/enums/payment.py
async_yookassa/enums/payment_details.py
async_yookassa/enums/payment_methods.py
async_yookassa/enums/payment_subject.py
async_yookassa/enums/payout.py
async_yookassa/enums/personal_data_enums.py
async_yookassa/enums/receipt_type.py
async_yookassa/enums/receiver.py
async_yookassa/enums/request_methods.py
async_yookassa/enums/settlement.py
async_yookassa/enums/transfers.py
async_yookassa/enums/vat_data.py
async_yookassa/enums/webhook_event.py
async_yookassa/exceptions/__init__.py
async_yookassa/exceptions/api_error.py
async_yookassa/exceptions/authorize_error.py
async_yookassa/exceptions/bad_request_error.py
async_yookassa/exceptions/configuration_errors.py
async_yookassa/exceptions/forbidden_error.py
async_yookassa/exceptions/not_found_error.py
async_yookassa/exceptions/response_processing_error.py
async_yookassa/exceptions/too_many_request_error.py
async_yookassa/exceptions/unauthorized_error.py
async_yookassa/models/__init__.py
async_yookassa/models/base.py
async_yookassa/models/list_options_base.py
async_yookassa/models/deal/__init__.py
async_yookassa/models/deal/request.py
async_yookassa/models/deal/response.py
async_yookassa/models/invoice/__init__.py
async_yookassa/models/invoice/cart.py
async_yookassa/models/invoice/delivery_method.py
async_yookassa/models/invoice/invoice_cancellation_details.py
async_yookassa/models/invoice/payment_details.py
async_yookassa/models/invoice/request.py
async_yookassa/models/invoice/response.py
async_yookassa/models/me/__init__.py
async_yookassa/models/me/fiscalization.py
async_yookassa-1.0.0.dist-info/licenses/LICENSE
async_yookassa-1.0.0.dist-info/METADATA
async_yookassa-1.0.0.dist-info/WHEEL
async_yookassa-1.0.0.dist-info/top_level.txt
async_yookassa-1.0.0.dist-info/RECORD
