Metadata-Version: 2.4
Name: async_yookassa
Version: 1.0.0
Summary: Unofficial API client for YooKassa
Author-email: prodream <sushkoos@gmail.com>
License-Expression: MIT
Project-URL: Repository, https://github.com/proDreams/async_yookassa
Keywords: yoomoney,yookassa,payout,sdk,python
Requires-Python: <3.15,>=3.11
License-File: LICENSE
Requires-Dist: pydantic[email]>=2.12.5
Requires-Dist: distro<2,>=1.9.0
Requires-Dist: httpx>=0.28.1
Dynamic: license-file
